mkdocs_ai_summary/__init__.py
mkdocs_ai_summary/ai_services.py
mkdocs_ai_summary/cache_manager.py
mkdocs_ai_summary/config_manager.py
mkdocs_ai_summary/content_processor.py
mkdocs_ai_summary/plugin.py
mkdocs_ai_summary_wcowin-1.2.2.dist-info/LICENSE
mkdocs_ai_summary_wcowin-1.2.2.dist-info/METADATA
mkdocs_ai_summary_wcowin-1.2.2.dist-info/WHEEL
mkdocs_ai_summary_wcowin-1.2.2.dist-info/entry_points.txt
mkdocs_ai_summary_wcowin-1.2.2.dist-info/top_level.txt
mkdocs_ai_summary_wcowin-1.2.2.dist-info/RECORD
