Metadata-Version: 2.1
Name: mkdocs-ai-summary-wcowin
Version: 1.2.2
Summary: AI-powered summary generation plugin for MkDocs Material
Home-page: https://github.com/Wcowin/Mkdocs-AI-Summary-Plus
Author: MkDocs AI Summary Team
Author-email: MkDocs AI Summary Team <support@mkdocs-ai-summary.com>
License: MIT
Project-URL: Documentation, https://github.com/Wcowin/Mkdocs-AI-Summary-Plus
Project-URL: Source, https://github.com/Wcowin/Mkdocs-AI-Summary-Plus
Project-URL: Tracker, https://github.com/Wcowin/Mkdocs-AI-Summary-Plus/issues
Keywords: mkdocs,plugin,ai,summary,documentation,markdown,material,openai,gemini,deepseek,glm
Classifier: Development Status :: 4 - Beta
Classifier: Intended Audience :: Developers
Classifier: License :: OSI Approved :: MIT License
Classifier: Operating System :: OS Independent
Classifier: Programming Language :: Python :: 3
Classifier: Programming Language :: Python :: 3.8
Classifier: Programming Language :: Python :: 3.9
Classifier: Programming Language :: Python :: 3.10
Classifier: Programming Language :: Python :: 3.11
Classifier: Programming Language :: Python :: 3.12
Classifier: Topic :: Documentation
Classifier: Topic :: Software Development :: Documentation
Classifier: Topic :: Text Processing :: Markup :: Markdown
Requires-Python: >=3.8
License-File: LICENSE
Requires-Dist: mkdocs (>=1.4.0)
Requires-Dist: requests (>=2.25.0)
Requires-Dist: python-dotenv (>=0.19.0)
Provides-Extra: dev
Requires-Dist: pytest (>=6.0) ; extra == 'dev'
Requires-Dist: pytest-cov (>=2.0) ; extra == 'dev'
Requires-Dist: black (>=21.0) ; extra == 'dev'
Requires-Dist: flake8 (>=3.8) ; extra == 'dev'
Requires-Dist: mypy (>=0.800) ; extra == 'dev'
Provides-Extra: test
Requires-Dist: pytest (>=6.0) ; extra == 'test'
Requires-Dist: pytest-cov (>=2.0) ; extra == 'test'
Requires-Dist: responses (>=0.18.0) ; extra == 'test'
